pip_ascent/InteractivePackageSelector.py
pip_ascent/PackageDetector.py
pip_ascent/PackageStatusDetector.py
pip_ascent/PackageUpgrader.py
pip_ascent/RequirementsDetector.py
pip_ascent/__init__.py
pip_ascent/cli.py
pip_ascent/requirements.txt
pip_ascent/virtualenv_checker.py
requirements/dev.txt
requirements/local.txt
requirements/production.txt
venv/bin/rst2html.py
venv/bin/rst2html4.py
venv/bin/rst2html5.py
venv/bin/rst2latex.py
venv/bin/rst2man.py
venv/bin/rst2odt.py
venv/bin/rst2odt_prepstyles.py
venv/bin/rst2pseudoxml.py
venv/bin/rst2s5.py
venv/bin/rst2xetex.py
venv/bin/rst2xml.py
venv/bin/rstpep2html.py
pip_ascent-0.1.2.dist-info/LICENSE
pip_ascent-0.1.2.dist-info/METADATA
pip_ascent-0.1.2.dist-info/WHEEL
pip_ascent-0.1.2.dist-info/entry_points.txt
pip_ascent-0.1.2.dist-info/top_level.txt
pip_ascent-0.1.2.dist-info/RECORD
