Metadata-Version: 2.1
Name: pip-ascent
Version: 0.1.2
Summary: A dynamic tool for upgrading pip requirements that seamlessly synchronizes the version changes within your requirements.txt file.
Home-page: https://github.com/thisisazeez/pip-ascent
Author: Abdulazeez Sherif
Author-email: Abdulazeez Sherif <abdoulazeezx@gmail.com>
License: The MIT License (MIT)
Project-URL: Homepage, https://github.com/thisisazeez/pip-ascent
Project-URL: Bug Tracker, https://github.com/thisisazeez/pip-ascent/issues
Keywords: cli,pip,pypi,requirements,upgrade
Classifier: Intended Audience :: Developers
Classifier: Topic :: Utilities
Classifier: License :: Public Domain
Classifier: Natural Language :: English
Classifier: Operating System :: OS Independent
Classifier: Programming Language :: Python :: 3
Classifier: Programming Language :: Python :: 3.8
Classifier: Programming Language :: Python :: 3.9
Classifier: Programming Language :: Python :: 3.10
Classifier: Programming Language :: Python :: 3.11
Requires-Python: >=3.10
License-File: LICENSE
Requires-Dist: docopt
Requires-Dist: packaging
Requires-Dist: requests
Requires-Dist: terminaltables
Requires-Dist: colorclass
Provides-Extra: test
Requires-Dist: coverage ; extra == 'test'
Requires-Dist: pytest ; extra == 'test'
Requires-Dist: pytest-cov ; extra == 'test'
Requires-Dist: pytest-pep8 ; extra == 'test'
Requires-Dist: mock ; extra == 'test'
Requires-Dist: responses ; extra == 'test'
